INSTALL.rst
LICENSE
MANIFEST.in
README.rst
VERSION
requirements.txt
setup.py
tasks.py
src/pong_game/__init__.py
src/pong_game/__main__.py
src/pong_game/__meta__.py
src/pong_game/pong.py
src/pong_game.egg-info/PKG-INFO
src/pong_game.egg-info/SOURCES.txt
src/pong_game.egg-info/dependency_links.txt
src/pong_game.egg-info/entry_points.txt
src/pong_game.egg-info/not-zip-safe
src/pong_game.egg-info/requires.txt
src/pong_game.egg-info/top_level.txt
src/pong_game/tests/__init__.py
src/pong_game/tests/__main__.py
src/pong_game/tests/test_documentation.py
src/pong_game/tests/test_pong_game.py